{
  "products": [
    {
      "id": "PROD001",
      "name": "Classic Navy Blue Suit",
      "category": "men",
      "subCategory": "business",
      "price": 12999,
      "discount": 30,
      "stock": 50,
      "description": "Premium wool blend suit with perfect tailoring. Perfect for business meetings and formal events.",
      "image": "https://images.unsplash.com/photo-1591047139829-d91aecb6caea?ixlib=rb-4.0.3&auto=format&fit=crop&w=800&q=80",
      "sizes": [
        "S",
        "M",
        "L",
        "XL",
        "XXL"
      ],
      "colors": [
        "Navy Blue",
        "Black",
        "White",
        "Gray"
      ],
      "rating": 3,
      "reviews": 1,
      "reviewsList": [
        {
          "id": "REV1768876687894",
          "userId": "USR1767091123021",
          "userName": "Ahmed",
          "rating": 3,
          "comment": "epic and best",
          "date": "2026-01-20T02:38:07.894Z"
        }
      ],
      "specifications": {
        "Material": "Premium Wool Blend",
        "Color": "Navy Blue",
        "Fit": "Regular Fit",
        "Occasion": "Formal, Business"
      },
      "createdAt": "2026-01-20T02:28:27.105Z"
    },
    {
      "id": "PROD002",
      "name": "Women's Formal Blazer",
      "category": "women",
      "subCategory": "",
      "price": 8999,
      "discount": 20,
      "stock": 35,
      "description": "Elegant formal blazer for professional women. Perfect for office wear and formal events.",
      "image": "https://images.unsplash.com/photo-1490481651871-ab68de25d43d?ixlib=rb-4.0.3&auto=format&fit=crop&w=800&q=80",
      "sizes": [
        "XS",
        "S",
        "M",
        "L"
      ],
      "colors": [
        "Black",
        "White",
        "Gray",
        "Navy"
      ],
      "rating": 0,
      "reviews": 0,
      "reviewsList": [],
      "specifications": {
        "Material": "Premium Polyester Blend",
        "Color": "Black",
        "Fit": "Regular Fit",
        "Occasion": "Office, Formal"
      },
      "createdAt": "2026-01-20T02:28:27.105Z"
    }
  ],
  "coupleProducts": [
    {
      "id": "COUP001",
      "name": "Royal Couple Suit Set",
      "maleImage": "https://images.unsplash.com/photo-1594938374184-f4938458c4a8?ixlib=rb-4.0.3&auto=format&fit=crop&w=800&q=80",
      "femaleImage": "https://images.unsplash.com/photo-1490481651871-ab68de25d43d?ixlib=rb-4.0.3&auto=format&fit=crop&w=800&q=80",
      "price": 19999,
      "discount": 15,
      "stock": 10,
      "description": "Perfectly matching suit set for couples. Ideal for weddings and special occasions.",
      "maleSize": [
        "S",
        "M",
        "L",
        "XL"
      ],
      "femaleSize": [
        "XS",
        "S",
        "M",
        "L"
      ],
      "rating": 0,
      "reviews": 0,
      "reviewsList": [],
      "createdAt": "2026-01-20T02:28:27.105Z"
    }
  ],
  "orders": [],
  "users": [],
  "contactMessages": [],
  "settings": {
    "storeName": "AS Styles",
    "storeEmail": "asstylesbuisness@gmail.com",
    "storePhone": "+923024693551",
    "storeAddress": "Near Baiga Paint Opposite Crystal Marriage Hall Lari Ada Road, Sargodh",
    "storeDescription": "Premium suits for every occasion. Quality and style guaranteed.",
    "storeHours": "Mon-Sat: 10AM-8PM, Sun: 12PM-6PM",
    "deliveryCharges": 299,
    "taxRate": 13,
    "codFee": 100,
    "easyPaisaNumber": "03024693551",
    "accountName": "Muhammad Saad Mirza",
    "updatedAt": "2026-01-20T02:28:27.105Z"
  },
  "subCategories": [
    {
      "id": "business",
      "category": "men",
      "name": "Business Suits",
      "description": "Professional suits for the workplace",
      "image": "https://images.unsplash.com/photo-1594938374184-f4938458c4a8?ixlib=rb-4.0.3&auto=format&fit=crop&w=800&q=80"
    },
    {
      "id": "wedding",
      "category": "men",
      "name": "Wedding Suits",
      "description": "Elegant suits for special occasions",
      "image": "https://images.unsplash.com/photo-1594938374184-f4938458c4a8?ixlib=rb-4.0.3&auto=format&fit=crop&w=800&q=80"
    },
    {
      "id": "formal",
      "category": "women",
      "name": "Formal Suits",
      "description": "Sophisticated suits for professional women",
      "image": "https://images.unsplash.com/photo-1490481651871-ab68de25d43d?ixlib=rb-4.0.3&auto=format&fit=crop&w=800&q=80"
    },
    {
      "id": "casual",
      "category": "women",
      "name": "Casual Blazers",
      "description": "Comfortable yet stylish casual wear",
      "image": "https://images.unsplash.com/photo-1490481651871-ab68de25d43d?ixlib=rb-4.0.3&auto=format&fit=crop&w=800&q=80"
    }
  ]
}